{
 "SigNoz/signoz": [
  [
   "14-04-2024",
   8,
   16796
  ],
  [
   "15-04-2024",
   10,
   16806
  ],
  [
   "16-04-2024",
   12,
   16818
  ],
  [
   "17-04-2024",
   11,
   16829
  ],
  [
   "18-04-2024",
   16,
   16845
  ],
  [
   "19-04-2024",
   9,
   16854
  ],
  [
   "20-04-2024",
   12,
   16866
  ],
  [
   "21-04-2024",
   8,
   16874
  ],
  [
   "22-04-2024",
   6,
   16880
  ],
  [
   "23-04-2024",
   6,
   16886
  ],
  [
   "24-04-2024",
   11,
   16897
  ],
  [
   "25-04-2024",
   16,
   16913
  ],
  [
   "26-04-2024",
   12,
   16925
  ],
  [
   "27-04-2024",
   11,
   16936
  ],
  [
   "28-04-2024",
   8,
   16944
  ],
  [
   "29-04-2024",
   6,
   16950
  ],
  [
   "30-04-2024",
   8,
   16958
  ],
  [
   "01-05-2024",
   7,
   16965
  ],
  [
   "02-05-2024",
   14,
   16979
  ],
  [
   "03-05-2024",
   16,
   16995
  ],
  [
   "04-05-2024",
   16,
   17011
  ],
  [
   "05-05-2024",
   4,
   17015
  ],
  [
   "06-05-2024",
   17,
   17032
  ],
  [
   "07-05-2024",
   15,
   17047
  ],
  [
   "08-05-2024",
   15,
   17062
  ],
  [
   "09-05-2024",
   9,
   17071
  ],
  [
   "10-05-2024",
   15,
   17086
  ],
  [
   "11-05-2024",
   7,
   17093
  ],
  [
   "12-05-2024",
   9,
   17102
  ],
  [
   "13-05-2024",
   13,
   17115
  ]
 ],
 "VictoriaMetrics/VictoriaMetrics": [
  [
   "14-04-2024",
   3,
   10755
  ],
  [
   "15-04-2024",
   7,
   10762
  ],
  [
   "16-04-2024",
   8,
   10770
  ],
  [
   "17-04-2024",
   6,
   10776
  ],
  [
   "18-04-2024",
   12,
   10788
  ],
  [
   "19-04-2024",
   6,
   10794
  ],
  [
   "20-04-2024",
   6,
   10800
  ],
  [
   "21-04-2024",
   3,
   10803
  ],
  [
   "22-04-2024",
   5,
   10808
  ],
  [
   "23-04-2024",
   7,
   10815
  ],
  [
   "24-04-2024",
   4,
   10819
  ],
  [
   "25-04-2024",
   9,
   10828
  ],
  [
   "26-04-2024",
   9,
   10837
  ],
  [
   "27-04-2024",
   10,
   10847
  ],
  [
   "28-04-2024",
   2,
   10849
  ],
  [
   "29-04-2024",
   7,
   10856
  ],
  [
   "30-04-2024",
   12,
   10868
  ],
  [
   "01-05-2024",
   8,
   10876
  ],
  [
   "02-05-2024",
   1,
   10877
  ],
  [
   "03-05-2024",
   3,
   10880
  ],
  [
   "04-05-2024",
   5,
   10885
  ],
  [
   "05-05-2024",
   4,
   10889
  ],
  [
   "06-05-2024",
   5,
   10894
  ],
  [
   "07-05-2024",
   5,
   10899
  ],
  [
   "08-05-2024",
   7,
   10906
  ],
  [
   "09-05-2024",
   6,
   10912
  ],
  [
   "10-05-2024",
   5,
   10917
  ],
  [
   "11-05-2024",
   3,
   10920
  ],
  [
   "12-05-2024",
   4,
   10924
  ],
  [
   "13-05-2024",
   7,
   10931
  ]
 ],
 "coroot/coroot": [
  [
   "14-04-2024",
   3,
   3465
  ],
  [
   "15-04-2024",
   1,
   3466
  ],
  [
   "16-04-2024",
   1,
   3467
  ],
  [
   "17-04-2024",
   1,
   3468
  ],
  [
   "18-04-2024",
   9,
   3477
  ],
  [
   "19-04-2024",
   10,
   3487
  ],
  [
   "20-04-2024",
   13,
   3500
  ],
  [
   "21-04-2024",
   0,
   3500
  ],
  [
   "22-04-2024",
   2,
   3502
  ],
  [
   "23-04-2024",
   5,
   3507
  ],
  [
   "24-04-2024",
   81,
   3588
  ],
  [
   "25-04-2024",
   84,
   3672
  ],
  [
   "26-04-2024",
   49,
   3721
  ],
  [
   "27-04-2024",
   36,
   3757
  ],
  [
   "28-04-2024",
   14,
   3771
  ],
  [
   "29-04-2024",
   18,
   3789
  ],
  [
   "30-04-2024",
   26,
   3815
  ],
  [
   "01-05-2024",
   25,
   3840
  ],
  [
   "02-05-2024",
   25,
   3865
  ],
  [
   "03-05-2024",
   18,
   3883
  ],
  [
   "04-05-2024",
   6,
   3889
  ],
  [
   "05-05-2024",
   59,
   3948
  ],
  [
   "06-05-2024",
   57,
   4005
  ],
  [
   "07-05-2024",
   44,
   4049
  ],
  [
   "08-05-2024",
   25,
   4074
  ],
  [
   "09-05-2024",
   23,
   4097
  ],
  [
   "10-05-2024",
   13,
   4110
  ],
  [
   "11-05-2024",
   13,
   4123
  ],
  [
   "12-05-2024",
   16,
   4139
  ],
  [
   "13-05-2024",
   1,
   4140
  ]
 ],
 "grafana/tempo": [
  [
   "14-04-2024",
   3,
   3602
  ],
  [
   "15-04-2024",
   1,
   3603
  ],
  [
   "16-04-2024",
   0,
   3603
  ],
  [
   "17-04-2024",
   3,
   3606
  ],
  [
   "18-04-2024",
   2,
   3608
  ],
  [
   "19-04-2024",
   3,
   3611
  ],
  [
   "20-04-2024",
   2,
   3613
  ],
  [
   "21-04-2024",
   0,
   3613
  ],
  [
   "22-04-2024",
   1,
   3614
  ],
  [
   "23-04-2024",
   2,
   3616
  ],
  [
   "24-04-2024",
   3,
   3619
  ],
  [
   "25-04-2024",
   2,
   3621
  ],
  [
   "26-04-2024",
   5,
   3626
  ],
  [
   "27-04-2024",
   4,
   3630
  ],
  [
   "28-04-2024",
   3,
   3633
  ],
  [
   "29-04-2024",
   0,
   3633
  ],
  [
   "30-04-2024",
   2,
   3635
  ],
  [
   "01-05-2024",
   3,
   3638
  ],
  [
   "02-05-2024",
   1,
   3639
  ],
  [
   "03-05-2024",
   1,
   3640
  ],
  [
   "04-05-2024",
   1,
   3641
  ],
  [
   "05-05-2024",
   1,
   3642
  ],
  [
   "06-05-2024",
   1,
   3643
  ],
  [
   "07-05-2024",
   0,
   3643
  ],
  [
   "08-05-2024",
   2,
   3645
  ],
  [
   "09-05-2024",
   3,
   3648
  ],
  [
   "10-05-2024",
   3,
   3651
  ],
  [
   "11-05-2024",
   2,
   3653
  ],
  [
   "12-05-2024",
   0,
   3653
  ],
  [
   "13-05-2024",
   1,
   3654
  ]
 ],
 "highlight/highlight": [
  [
   "14-04-2024",
   6,
   6821
  ],
  [
   "15-04-2024",
   12,
   6833
  ],
  [
   "16-04-2024",
   8,
   6841
  ],
  [
   "17-04-2024",
   11,
   6852
  ],
  [
   "18-04-2024",
   12,
   6864
  ],
  [
   "19-04-2024",
   7,
   6871
  ],
  [
   "20-04-2024",
   4,
   6875
  ],
  [
   "21-04-2024",
   4,
   6879
  ],
  [
   "22-04-2024",
   7,
   6886
  ],
  [
   "23-04-2024",
   5,
   6891
  ],
  [
   "24-04-2024",
   14,
   6905
  ],
  [
   "25-04-2024",
   7,
   6912
  ],
  [
   "26-04-2024",
   10,
   6922
  ],
  [
   "27-04-2024",
   4,
   6926
  ],
  [
   "28-04-2024",
   2,
   6928
  ],
  [
   "29-04-2024",
   6,
   6934
  ],
  [
   "30-04-2024",
   2,
   6936
  ],
  [
   "01-05-2024",
   4,
   6940
  ],
  [
   "02-05-2024",
   1,
   6941
  ],
  [
   "03-05-2024",
   4,
   6945
  ],
  [
   "04-05-2024",
   1,
   6946
  ],
  [
   "05-05-2024",
   3,
   6949
  ],
  [
   "06-05-2024",
   7,
   6956
  ],
  [
   "07-05-2024",
   4,
   6960
  ],
  [
   "08-05-2024",
   3,
   6963
  ],
  [
   "09-05-2024",
   4,
   6967
  ],
  [
   "10-05-2024",
   5,
   6972
  ],
  [
   "11-05-2024",
   5,
   6977
  ],
  [
   "12-05-2024",
   2,
   6979
  ],
  [
   "13-05-2024",
   8,
   6987
  ]
 ],
 "hyperdxio/hyperdx": [
  [
   "14-04-2024",
   6,
   6024
  ],
  [
   "15-04-2024",
   2,
   6026
  ],
  [
   "16-04-2024",
   14,
   6040
  ],
  [
   "17-04-2024",
   9,
   6049
  ],
  [
   "18-04-2024",
   5,
   6054
  ],
  [
   "19-04-2024",
   5,
   6059
  ],
  [
   "20-04-2024",
   6,
   6065
  ],
  [
   "21-04-2024",
   3,
   6068
  ],
  [
   "22-04-2024",
   4,
   6072
  ],
  [
   "23-04-2024",
   2,
   6074
  ],
  [
   "24-04-2024",
   9,
   6083
  ],
  [
   "25-04-2024",
   6,
   6089
  ],
  [
   "26-04-2024",
   9,
   6098
  ],
  [
   "27-04-2024",
   5,
   6103
  ],
  [
   "28-04-2024",
   6,
   6109
  ],
  [
   "29-04-2024",
   6,
   6115
  ],
  [
   "30-04-2024",
   5,
   6120
  ],
  [
   "01-05-2024",
   5,
   6125
  ],
  [
   "02-05-2024",
   5,
   6130
  ],
  [
   "03-05-2024",
   3,
   6133
  ],
  [
   "04-05-2024",
   6,
   6139
  ],
  [
   "05-05-2024",
   5,
   6144
  ],
  [
   "06-05-2024",
   4,
   6148
  ],
  [
   "07-05-2024",
   7,
   6155
  ],
  [
   "08-05-2024",
   4,
   6159
  ],
  [
   "09-05-2024",
   2,
   6161
  ],
  [
   "10-05-2024",
   5,
   6166
  ],
  [
   "11-05-2024",
   2,
   6168
  ],
  [
   "12-05-2024",
   1,
   6169
  ],
  [
   "13-05-2024",
   2,
   6171
  ]
 ],
 "jaegertracing/jaeger": [
  [
   "14-04-2024",
   6,
   19324
  ],
  [
   "15-04-2024",
   4,
   19328
  ],
  [
   "16-04-2024",
   9,
   19337
  ],
  [
   "17-04-2024",
   5,
   19342
  ],
  [
   "18-04-2024",
   4,
   19346
  ],
  [
   "19-04-2024",
   5,
   19351
  ],
  [
   "20-04-2024",
   3,
   19354
  ],
  [
   "21-04-2024",
   7,
   19361
  ],
  [
   "22-04-2024",
   8,
   19369
  ],
  [
   "23-04-2024",
   3,
   19372
  ],
  [
   "24-04-2024",
   6,
   19378
  ],
  [
   "25-04-2024",
   10,
   19388
  ],
  [
   "26-04-2024",
   6,
   19394
  ],
  [
   "27-04-2024",
   6,
   19400
  ],
  [
   "28-04-2024",
   20,
   19420
  ],
  [
   "29-04-2024",
   27,
   19447
  ],
  [
   "30-04-2024",
   15,
   19462
  ],
  [
   "01-05-2024",
   11,
   19473
  ],
  [
   "02-05-2024",
   8,
   19481
  ],
  [
   "03-05-2024",
   9,
   19490
  ],
  [
   "04-05-2024",
   5,
   19495
  ],
  [
   "05-05-2024",
   9,
   19504
  ],
  [
   "06-05-2024",
   4,
   19508
  ],
  [
   "07-05-2024",
   8,
   19516
  ],
  [
   "08-05-2024",
   12,
   19528
  ],
  [
   "09-05-2024",
   9,
   19537
  ],
  [
   "10-05-2024",
   4,
   19541
  ],
  [
   "11-05-2024",
   7,
   19548
  ],
  [
   "12-05-2024",
   6,
   19554
  ],
  [
   "13-05-2024",
   4,
   19558
  ]
 ],
 "keyval-dev/odigos": [
  [
   "14-04-2024",
   1,
   3002
  ],
  [
   "15-04-2024",
   0,
   3002
  ],
  [
   "16-04-2024",
   1,
   3003
  ],
  [
   "17-04-2024",
   0,
   3003
  ],
  [
   "18-04-2024",
   2,
   3005
  ],
  [
   "19-04-2024",
   3,
   3008
  ],
  [
   "20-04-2024",
   0,
   3008
  ],
  [
   "21-04-2024",
   1,
   3009
  ],
  [
   "22-04-2024",
   0,
   3009
  ],
  [
   "23-04-2024",
   3,
   3012
  ],
  [
   "24-04-2024",
   2,
   3014
  ],
  [
   "25-04-2024",
   2,
   3016
  ],
  [
   "26-04-2024",
   0,
   3016
  ],
  [
   "27-04-2024",
   1,
   3017
  ],
  [
   "28-04-2024",
   1,
   3018
  ],
  [
   "29-04-2024",
   1,
   3019
  ],
  [
   "30-04-2024",
   0,
   3019
  ],
  [
   "01-05-2024",
   1,
   3020
  ],
  [
   "02-05-2024",
   1,
   3021
  ],
  [
   "03-05-2024",
   2,
   3023
  ],
  [
   "04-05-2024",
   2,
   3025
  ],
  [
   "05-05-2024",
   3,
   3028
  ],
  [
   "06-05-2024",
   1,
   3029
  ],
  [
   "07-05-2024",
   1,
   3030
  ],
  [
   "08-05-2024",
   2,
   3032
  ],
  [
   "09-05-2024",
   4,
   3036
  ],
  [
   "10-05-2024",
   2,
   3038
  ],
  [
   "11-05-2024",
   2,
   3040
  ],
  [
   "12-05-2024",
   0,
   3040
  ],
  [
   "13-05-2024",
   0,
   3040
  ]
 ],
 "openobserve/openobserve": [
  [
   "14-04-2024",
   6,
   9278
  ],
  [
   "15-04-2024",
   7,
   9285
  ],
  [
   "16-04-2024",
   10,
   9295
  ],
  [
   "17-04-2024",
   6,
   9301
  ],
  [
   "18-04-2024",
   2,
   9303
  ],
  [
   "19-04-2024",
   18,
   9321
  ],
  [
   "20-04-2024",
   21,
   9342
  ],
  [
   "21-04-2024",
   5,
   9347
  ],
  [
   "22-04-2024",
   13,
   9360
  ],
  [
   "23-04-2024",
   12,
   9372
  ],
  [
   "24-04-2024",
   13,
   9385
  ],
  [
   "25-04-2024",
   12,
   9397
  ],
  [
   "26-04-2024",
   7,
   9404
  ],
  [
   "27-04-2024",
   8,
   9412
  ],
  [
   "28-04-2024",
   10,
   9422
  ],
  [
   "29-04-2024",
   14,
   9436
  ],
  [
   "30-04-2024",
   27,
   9463
  ],
  [
   "01-05-2024",
   74,
   9537
  ],
  [
   "02-05-2024",
   50,
   9587
  ],
  [
   "03-05-2024",
   34,
   9621
  ],
  [
   "04-05-2024",
   16,
   9637
  ],
  [
   "05-05-2024",
   12,
   9649
  ],
  [
   "06-05-2024",
   12,
   9661
  ],
  [
   "07-05-2024",
   18,
   9679
  ],
  [
   "08-05-2024",
   18,
   9697
  ],
  [
   "09-05-2024",
   9,
   9706
  ],
  [
   "10-05-2024",
   11,
   9717
  ],
  [
   "11-05-2024",
   13,
   9730
  ],
  [
   "12-05-2024",
   13,
   9743
  ],
  [
   "13-05-2024",
   8,
   9751
  ]
 ],
 "openzipkin/zipkin": [
  [
   "14-04-2024",
   2,
   16689
  ],
  [
   "15-04-2024",
   5,
   16694
  ],
  [
   "16-04-2024",
   4,
   16698
  ],
  [
   "17-04-2024",
   1,
   16699
  ],
  [
   "18-04-2024",
   0,
   16699
  ],
  [
   "19-04-2024",
   4,
   16703
  ],
  [
   "20-04-2024",
   3,
   16706
  ],
  [
   "21-04-2024",
   1,
   16707
  ],
  [
   "22-04-2024",
   1,
   16708
  ],
  [
   "23-04-2024",
   1,
   16709
  ],
  [
   "24-04-2024",
   6,
   16715
  ],
  [
   "25-04-2024",
   5,
   16720
  ],
  [
   "26-04-2024",
   3,
   16723
  ],
  [
   "27-04-2024",
   1,
   16724
  ],
  [
   "28-04-2024",
   4,
   16728
  ],
  [
   "29-04-2024",
   3,
   16731
  ],
  [
   "30-04-2024",
   3,
   16734
  ],
  [
   "01-05-2024",
   2,
   16736
  ],
  [
   "02-05-2024",
   0,
   16736
  ],
  [
   "03-05-2024",
   2,
   16738
  ],
  [
   "04-05-2024",
   0,
   16738
  ],
  [
   "05-05-2024",
   2,
   16740
  ],
  [
   "06-05-2024",
   2,
   16742
  ],
  [
   "07-05-2024",
   2,
   16744
  ],
  [
   "08-05-2024",
   1,
   16745
  ],
  [
   "09-05-2024",
   0,
   16745
  ],
  [
   "10-05-2024",
   3,
   16748
  ],
  [
   "11-05-2024",
   4,
   16752
  ],
  [
   "12-05-2024",
   3,
   16755
  ],
  [
   "13-05-2024",
   3,
   16758
  ]
 ],
 "quickwit-oss/quickwit": [
  [
   "14-04-2024",
   5,
   5987
  ],
  [
   "15-04-2024",
   7,
   5994
  ],
  [
   "16-04-2024",
   8,
   6002
  ],
  [
   "17-04-2024",
   12,
   6014
  ],
  [
   "18-04-2024",
   11,
   6025
  ],
  [
   "19-04-2024",
   7,
   6032
  ],
  [
   "20-04-2024",
   10,
   6042
  ],
  [
   "21-04-2024",
   5,
   6047
  ],
  [
   "22-04-2024",
   10,
   6057
  ],
  [
   "23-04-2024",
   10,
   6067
  ],
  [
   "24-04-2024",
   9,
   6076
  ],
  [
   "25-04-2024",
   2,
   6078
  ],
  [
   "26-04-2024",
   7,
   6085
  ],
  [
   "27-04-2024",
   5,
   6090
  ],
  [
   "28-04-2024",
   9,
   6099
  ],
  [
   "29-04-2024",
   6,
   6105
  ],
  [
   "30-04-2024",
   22,
   6127
  ],
  [
   "01-05-2024",
   5,
   6132
  ],
  [
   "02-05-2024",
   5,
   6137
  ],
  [
   "03-05-2024",
   6,
   6143
  ],
  [
   "04-05-2024",
   5,
   6148
  ],
  [
   "05-05-2024",
   4,
   6152
  ],
  [
   "06-05-2024",
   3,
   6155
  ],
  [
   "07-05-2024",
   4,
   6159
  ],
  [
   "08-05-2024",
   8,
   6167
  ],
  [
   "09-05-2024",
   1,
   6168
  ],
  [
   "10-05-2024",
   2,
   6170
  ],
  [
   "11-05-2024",
   3,
   6173
  ],
  [
   "12-05-2024",
   1,
   6174
  ],
  [
   "13-05-2024",
   2,
   6176
  ]
 ],
 "uptrace/uptrace": [
  [
   "14-04-2024",
   2,
   2855
  ],
  [
   "15-04-2024",
   1,
   2856
  ],
  [
   "16-04-2024",
   3,
   2859
  ],
  [
   "17-04-2024",
   4,
   2863
  ],
  [
   "18-04-2024",
   6,
   2869
  ],
  [
   "19-04-2024",
   5,
   2874
  ],
  [
   "20-04-2024",
   1,
   2875
  ],
  [
   "21-04-2024",
   2,
   2877
  ],
  [
   "22-04-2024",
   1,
   2878
  ],
  [
   "23-04-2024",
   6,
   2884
  ],
  [
   "24-04-2024",
   2,
   2886
  ],
  [
   "25-04-2024",
   2,
   2888
  ],
  [
   "26-04-2024",
   2,
   2890
  ],
  [
   "27-04-2024",
   7,
   2897
  ],
  [
   "28-04-2024",
   2,
   2899
  ],
  [
   "29-04-2024",
   4,
   2903
  ],
  [
   "30-04-2024",
   4,
   2907
  ],
  [
   "01-05-2024",
   2,
   2909
  ],
  [
   "02-05-2024",
   1,
   2910
  ],
  [
   "03-05-2024",
   2,
   2912
  ],
  [
   "04-05-2024",
   2,
   2914
  ],
  [
   "05-05-2024",
   0,
   2914
  ],
  [
   "06-05-2024",
   0,
   2914
  ],
  [
   "07-05-2024",
   4,
   2918
  ],
  [
   "08-05-2024",
   2,
   2920
  ],
  [
   "09-05-2024",
   1,
   2921
  ],
  [
   "10-05-2024",
   3,
   2924
  ],
  [
   "11-05-2024",
   1,
   2925
  ],
  [
   "12-05-2024",
   4,
   2929
  ],
  [
   "13-05-2024",
   4,
   2933
  ]
 ]
}