{
 "SigNoz/signoz": [
  [
   "03-03-2024",
   10,
   16377
  ],
  [
   "04-03-2024",
   8,
   16385
  ],
  [
   "05-03-2024",
   11,
   16396
  ],
  [
   "06-03-2024",
   9,
   16405
  ],
  [
   "07-03-2024",
   20,
   16425
  ],
  [
   "08-03-2024",
   13,
   16438
  ],
  [
   "09-03-2024",
   8,
   16446
  ],
  [
   "10-03-2024",
   9,
   16455
  ],
  [
   "11-03-2024",
   9,
   16464
  ],
  [
   "12-03-2024",
   11,
   16475
  ],
  [
   "13-03-2024",
   16,
   16491
  ],
  [
   "14-03-2024",
   16,
   16507
  ],
  [
   "15-03-2024",
   17,
   16524
  ],
  [
   "16-03-2024",
   22,
   16546
  ],
  [
   "17-03-2024",
   7,
   16553
  ],
  [
   "18-03-2024",
   7,
   16560
  ],
  [
   "19-03-2024",
   9,
   16569
  ],
  [
   "20-03-2024",
   11,
   16580
  ],
  [
   "21-03-2024",
   10,
   16590
  ],
  [
   "22-03-2024",
   12,
   16602
  ],
  [
   "23-03-2024",
   13,
   16615
  ],
  [
   "24-03-2024",
   14,
   16629
  ],
  [
   "25-03-2024",
   12,
   16641
  ],
  [
   "26-03-2024",
   7,
   16648
  ],
  [
   "27-03-2024",
   16,
   16664
  ],
  [
   "28-03-2024",
   11,
   16675
  ],
  [
   "29-03-2024",
   11,
   16686
  ],
  [
   "30-03-2024",
   11,
   16697
  ],
  [
   "31-03-2024",
   7,
   16704
  ],
  [
   "01-04-2024",
   7,
   16711
  ]
 ],
 "VictoriaMetrics/VictoriaMetrics": [
  [
   "03-03-2024",
   2,
   10490
  ],
  [
   "04-03-2024",
   6,
   10496
  ],
  [
   "05-03-2024",
   5,
   10501
  ],
  [
   "06-03-2024",
   8,
   10509
  ],
  [
   "07-03-2024",
   11,
   10520
  ],
  [
   "08-03-2024",
   4,
   10524
  ],
  [
   "09-03-2024",
   4,
   10528
  ],
  [
   "10-03-2024",
   6,
   10534
  ],
  [
   "11-03-2024",
   2,
   10536
  ],
  [
   "12-03-2024",
   7,
   10543
  ],
  [
   "13-03-2024",
   4,
   10547
  ],
  [
   "14-03-2024",
   7,
   10554
  ],
  [
   "15-03-2024",
   7,
   10561
  ],
  [
   "16-03-2024",
   7,
   10568
  ],
  [
   "17-03-2024",
   4,
   10572
  ],
  [
   "18-03-2024",
   5,
   10577
  ],
  [
   "19-03-2024",
   14,
   10591
  ],
  [
   "20-03-2024",
   8,
   10599
  ],
  [
   "21-03-2024",
   12,
   10611
  ],
  [
   "22-03-2024",
   13,
   10624
  ],
  [
   "23-03-2024",
   12,
   10636
  ],
  [
   "24-03-2024",
   4,
   10640
  ],
  [
   "25-03-2024",
   4,
   10644
  ],
  [
   "26-03-2024",
   4,
   10648
  ],
  [
   "27-03-2024",
   3,
   10651
  ],
  [
   "28-03-2024",
   13,
   10664
  ],
  [
   "29-03-2024",
   9,
   10673
  ],
  [
   "30-03-2024",
   6,
   10679
  ],
  [
   "31-03-2024",
   2,
   10681
  ],
  [
   "01-04-2024",
   4,
   10685
  ]
 ],
 "grafana/tempo": [
  [
   "03-03-2024",
   0,
   3525
  ],
  [
   "04-03-2024",
   3,
   3528
  ],
  [
   "05-03-2024",
   5,
   3533
  ],
  [
   "06-03-2024",
   4,
   3537
  ],
  [
   "07-03-2024",
   4,
   3541
  ],
  [
   "08-03-2024",
   2,
   3543
  ],
  [
   "09-03-2024",
   1,
   3544
  ],
  [
   "10-03-2024",
   1,
   3545
  ],
  [
   "11-03-2024",
   1,
   3546
  ],
  [
   "12-03-2024",
   4,
   3550
  ],
  [
   "13-03-2024",
   2,
   3552
  ],
  [
   "14-03-2024",
   1,
   3553
  ],
  [
   "15-03-2024",
   3,
   3556
  ],
  [
   "16-03-2024",
   2,
   3558
  ],
  [
   "17-03-2024",
   1,
   3559
  ],
  [
   "18-03-2024",
   2,
   3561
  ],
  [
   "19-03-2024",
   0,
   3561
  ],
  [
   "20-03-2024",
   3,
   3564
  ],
  [
   "21-03-2024",
   3,
   3567
  ],
  [
   "22-03-2024",
   1,
   3568
  ],
  [
   "23-03-2024",
   1,
   3569
  ],
  [
   "24-03-2024",
   0,
   3569
  ],
  [
   "25-03-2024",
   2,
   3571
  ],
  [
   "26-03-2024",
   1,
   3572
  ],
  [
   "27-03-2024",
   1,
   3573
  ],
  [
   "28-03-2024",
   2,
   3575
  ],
  [
   "29-03-2024",
   3,
   3578
  ],
  [
   "30-03-2024",
   2,
   3580
  ],
  [
   "31-03-2024",
   0,
   3580
  ],
  [
   "01-04-2024",
   2,
   3582
  ]
 ],
 "highlight/highlight": [
  [
   "03-03-2024",
   2,
   6583
  ],
  [
   "04-03-2024",
   4,
   6587
  ],
  [
   "05-03-2024",
   2,
   6589
  ],
  [
   "06-03-2024",
   6,
   6595
  ],
  [
   "07-03-2024",
   4,
   6599
  ],
  [
   "08-03-2024",
   8,
   6607
  ],
  [
   "09-03-2024",
   8,
   6615
  ],
  [
   "10-03-2024",
   4,
   6619
  ],
  [
   "11-03-2024",
   5,
   6624
  ],
  [
   "12-03-2024",
   6,
   6630
  ],
  [
   "13-03-2024",
   8,
   6638
  ],
  [
   "14-03-2024",
   7,
   6645
  ],
  [
   "15-03-2024",
   7,
   6652
  ],
  [
   "16-03-2024",
   4,
   6656
  ],
  [
   "17-03-2024",
   1,
   6657
  ],
  [
   "18-03-2024",
   4,
   6661
  ],
  [
   "19-03-2024",
   5,
   6666
  ],
  [
   "20-03-2024",
   2,
   6668
  ],
  [
   "21-03-2024",
   6,
   6674
  ],
  [
   "22-03-2024",
   5,
   6679
  ],
  [
   "23-03-2024",
   9,
   6688
  ],
  [
   "24-03-2024",
   4,
   6692
  ],
  [
   "25-03-2024",
   2,
   6694
  ],
  [
   "26-03-2024",
   6,
   6700
  ],
  [
   "27-03-2024",
   5,
   6705
  ],
  [
   "28-03-2024",
   9,
   6714
  ],
  [
   "29-03-2024",
   7,
   6721
  ],
  [
   "30-03-2024",
   3,
   6724
  ],
  [
   "31-03-2024",
   2,
   6726
  ],
  [
   "01-04-2024",
   2,
   6728
  ]
 ],
 "hyperdxio/hyperdx": [
  [
   "03-03-2024",
   2,
   5635
  ],
  [
   "04-03-2024",
   5,
   5640
  ],
  [
   "05-03-2024",
   1,
   5641
  ],
  [
   "06-03-2024",
   4,
   5645
  ],
  [
   "07-03-2024",
   12,
   5657
  ],
  [
   "08-03-2024",
   0,
   5657
  ],
  [
   "09-03-2024",
   2,
   5659
  ],
  [
   "10-03-2024",
   4,
   5663
  ],
  [
   "11-03-2024",
   3,
   5666
  ],
  [
   "12-03-2024",
   5,
   5671
  ],
  [
   "13-03-2024",
   4,
   5675
  ],
  [
   "14-03-2024",
   3,
   5678
  ],
  [
   "15-03-2024",
   2,
   5680
  ],
  [
   "16-03-2024",
   5,
   5685
  ],
  [
   "17-03-2024",
   3,
   5688
  ],
  [
   "18-03-2024",
   4,
   5692
  ],
  [
   "19-03-2024",
   2,
   5694
  ],
  [
   "20-03-2024",
   4,
   5698
  ],
  [
   "21-03-2024",
   1,
   5699
  ],
  [
   "22-03-2024",
   4,
   5703
  ],
  [
   "23-03-2024",
   2,
   5705
  ],
  [
   "24-03-2024",
   1,
   5706
  ],
  [
   "25-03-2024",
   1,
   5707
  ],
  [
   "26-03-2024",
   3,
   5710
  ],
  [
   "27-03-2024",
   3,
   5713
  ],
  [
   "28-03-2024",
   4,
   5717
  ],
  [
   "29-03-2024",
   4,
   5721
  ],
  [
   "30-03-2024",
   2,
   5723
  ],
  [
   "31-03-2024",
   2,
   5725
  ],
  [
   "01-04-2024",
   31,
   5756
  ]
 ],
 "jaegertracing/jaeger": [
  [
   "03-03-2024",
   2,
   19111
  ],
  [
   "04-03-2024",
   4,
   19115
  ],
  [
   "05-03-2024",
   10,
   19125
  ],
  [
   "06-03-2024",
   11,
   19136
  ],
  [
   "07-03-2024",
   10,
   19146
  ],
  [
   "08-03-2024",
   9,
   19155
  ],
  [
   "09-03-2024",
   6,
   19161
  ],
  [
   "10-03-2024",
   3,
   19164
  ],
  [
   "11-03-2024",
   7,
   19171
  ],
  [
   "12-03-2024",
   8,
   19179
  ],
  [
   "13-03-2024",
   10,
   19189
  ],
  [
   "14-03-2024",
   4,
   19193
  ],
  [
   "15-03-2024",
   11,
   19204
  ],
  [
   "16-03-2024",
   5,
   19209
  ],
  [
   "17-03-2024",
   4,
   19213
  ],
  [
   "18-03-2024",
   5,
   19218
  ],
  [
   "19-03-2024",
   3,
   19221
  ],
  [
   "20-03-2024",
   7,
   19228
  ],
  [
   "21-03-2024",
   6,
   19234
  ],
  [
   "22-03-2024",
   4,
   19238
  ],
  [
   "23-03-2024",
   10,
   19248
  ],
  [
   "24-03-2024",
   7,
   19255
  ],
  [
   "25-03-2024",
   6,
   19261
  ],
  [
   "26-03-2024",
   4,
   19265
  ],
  [
   "27-03-2024",
   5,
   19270
  ],
  [
   "28-03-2024",
   4,
   19274
  ],
  [
   "29-03-2024",
   6,
   19280
  ],
  [
   "30-03-2024",
   3,
   19283
  ],
  [
   "31-03-2024",
   5,
   19288
  ],
  [
   "01-04-2024",
   3,
   19291
  ]
 ],
 "keyval-dev/odigos": [
  [
   "03-03-2024",
   3,
   2919
  ],
  [
   "04-03-2024",
   0,
   2919
  ],
  [
   "05-03-2024",
   2,
   2921
  ],
  [
   "06-03-2024",
   13,
   2934
  ],
  [
   "07-03-2024",
   11,
   2945
  ],
  [
   "08-03-2024",
   2,
   2947
  ],
  [
   "09-03-2024",
   4,
   2951
  ],
  [
   "10-03-2024",
   7,
   2958
  ],
  [
   "11-03-2024",
   1,
   2959
  ],
  [
   "12-03-2024",
   2,
   2961
  ],
  [
   "13-03-2024",
   1,
   2962
  ],
  [
   "14-03-2024",
   3,
   2965
  ],
  [
   "15-03-2024",
   1,
   2966
  ],
  [
   "16-03-2024",
   3,
   2969
  ],
  [
   "17-03-2024",
   0,
   2969
  ],
  [
   "18-03-2024",
   2,
   2971
  ],
  [
   "19-03-2024",
   2,
   2973
  ],
  [
   "20-03-2024",
   0,
   2973
  ],
  [
   "21-03-2024",
   0,
   2973
  ],
  [
   "22-03-2024",
   2,
   2975
  ],
  [
   "23-03-2024",
   3,
   2978
  ],
  [
   "24-03-2024",
   1,
   2979
  ],
  [
   "25-03-2024",
   3,
   2982
  ],
  [
   "26-03-2024",
   1,
   2983
  ],
  [
   "27-03-2024",
   3,
   2986
  ],
  [
   "28-03-2024",
   2,
   2988
  ],
  [
   "29-03-2024",
   1,
   2989
  ],
  [
   "30-03-2024",
   1,
   2990
  ],
  [
   "31-03-2024",
   0,
   2990
  ],
  [
   "01-04-2024",
   1,
   2991
  ]
 ],
 "openobserve/openobserve": [
  [
   "03-03-2024",
   7,
   8592
  ],
  [
   "04-03-2024",
   5,
   8597
  ],
  [
   "05-03-2024",
   19,
   8616
  ],
  [
   "06-03-2024",
   10,
   8626
  ],
  [
   "07-03-2024",
   13,
   8639
  ],
  [
   "08-03-2024",
   11,
   8650
  ],
  [
   "09-03-2024",
   15,
   8665
  ],
  [
   "10-03-2024",
   10,
   8675
  ],
  [
   "11-03-2024",
   5,
   8680
  ],
  [
   "12-03-2024",
   12,
   8692
  ],
  [
   "13-03-2024",
   10,
   8702
  ],
  [
   "14-03-2024",
   11,
   8713
  ],
  [
   "15-03-2024",
   12,
   8725
  ],
  [
   "16-03-2024",
   17,
   8742
  ],
  [
   "17-03-2024",
   11,
   8753
  ],
  [
   "18-03-2024",
   9,
   8762
  ],
  [
   "19-03-2024",
   9,
   8771
  ],
  [
   "20-03-2024",
   9,
   8780
  ],
  [
   "21-03-2024",
   14,
   8794
  ],
  [
   "22-03-2024",
   17,
   8811
  ],
  [
   "23-03-2024",
   10,
   8821
  ],
  [
   "24-03-2024",
   4,
   8825
  ],
  [
   "25-03-2024",
   7,
   8832
  ],
  [
   "26-03-2024",
   9,
   8841
  ],
  [
   "27-03-2024",
   11,
   8852
  ],
  [
   "28-03-2024",
   13,
   8865
  ],
  [
   "29-03-2024",
   16,
   8881
  ],
  [
   "30-03-2024",
   21,
   8902
  ],
  [
   "31-03-2024",
   24,
   8926
  ],
  [
   "01-04-2024",
   17,
   8943
  ]
 ],
 "openzipkin/zipkin": [
  [
   "03-03-2024",
   3,
   16607
  ],
  [
   "04-03-2024",
   3,
   16610
  ],
  [
   "05-03-2024",
   3,
   16613
  ],
  [
   "06-03-2024",
   2,
   16615
  ],
  [
   "07-03-2024",
   4,
   16619
  ],
  [
   "08-03-2024",
   1,
   16620
  ],
  [
   "09-03-2024",
   3,
   16623
  ],
  [
   "10-03-2024",
   2,
   16625
  ],
  [
   "11-03-2024",
   6,
   16631
  ],
  [
   "12-03-2024",
   3,
   16634
  ],
  [
   "13-03-2024",
   1,
   16635
  ],
  [
   "14-03-2024",
   2,
   16637
  ],
  [
   "15-03-2024",
   3,
   16640
  ],
  [
   "16-03-2024",
   1,
   16641
  ],
  [
   "17-03-2024",
   1,
   16642
  ],
  [
   "18-03-2024",
   1,
   16643
  ],
  [
   "19-03-2024",
   5,
   16648
  ],
  [
   "20-03-2024",
   3,
   16651
  ],
  [
   "21-03-2024",
   2,
   16653
  ],
  [
   "22-03-2024",
   2,
   16655
  ],
  [
   "23-03-2024",
   3,
   16658
  ],
  [
   "24-03-2024",
   1,
   16659
  ],
  [
   "25-03-2024",
   6,
   16665
  ],
  [
   "26-03-2024",
   2,
   16667
  ],
  [
   "27-03-2024",
   3,
   16670
  ],
  [
   "28-03-2024",
   6,
   16676
  ],
  [
   "29-03-2024",
   2,
   16678
  ],
  [
   "30-03-2024",
   1,
   16679
  ],
  [
   "31-03-2024",
   2,
   16681
  ],
  [
   "01-04-2024",
   1,
   16682
  ]
 ],
 "quickwit-oss/quickwit": [
  [
   "03-03-2024",
   2,
   5490
  ],
  [
   "04-03-2024",
   3,
   5493
  ],
  [
   "05-03-2024",
   6,
   5499
  ],
  [
   "06-03-2024",
   6,
   5505
  ],
  [
   "07-03-2024",
   6,
   5511
  ],
  [
   "08-03-2024",
   1,
   5512
  ],
  [
   "09-03-2024",
   16,
   5528
  ],
  [
   "10-03-2024",
   7,
   5535
  ],
  [
   "11-03-2024",
   6,
   5541
  ],
  [
   "12-03-2024",
   6,
   5547
  ],
  [
   "13-03-2024",
   6,
   5553
  ],
  [
   "14-03-2024",
   6,
   5559
  ],
  [
   "15-03-2024",
   9,
   5568
  ],
  [
   "16-03-2024",
   5,
   5573
  ],
  [
   "17-03-2024",
   6,
   5579
  ],
  [
   "18-03-2024",
   2,
   5581
  ],
  [
   "19-03-2024",
   4,
   5585
  ],
  [
   "20-03-2024",
   14,
   5599
  ],
  [
   "21-03-2024",
   11,
   5610
  ],
  [
   "22-03-2024",
   14,
   5624
  ],
  [
   "23-03-2024",
   22,
   5646
  ],
  [
   "24-03-2024",
   50,
   5696
  ],
  [
   "25-03-2024",
   37,
   5733
  ],
  [
   "26-03-2024",
   32,
   5765
  ],
  [
   "27-03-2024",
   7,
   5772
  ],
  [
   "28-03-2024",
   10,
   5782
  ],
  [
   "29-03-2024",
   9,
   5791
  ],
  [
   "30-03-2024",
   9,
   5800
  ],
  [
   "31-03-2024",
   3,
   5803
  ],
  [
   "01-04-2024",
   13,
   5816
  ]
 ],
 "uptrace/uptrace": [
  [
   "03-03-2024",
   2,
   2731
  ],
  [
   "04-03-2024",
   1,
   2732
  ],
  [
   "05-03-2024",
   6,
   2738
  ],
  [
   "06-03-2024",
   4,
   2742
  ],
  [
   "07-03-2024",
   4,
   2746
  ],
  [
   "08-03-2024",
   3,
   2749
  ],
  [
   "09-03-2024",
   3,
   2752
  ],
  [
   "10-03-2024",
   1,
   2753
  ],
  [
   "11-03-2024",
   3,
   2756
  ],
  [
   "12-03-2024",
   4,
   2760
  ],
  [
   "13-03-2024",
   7,
   2767
  ],
  [
   "14-03-2024",
   5,
   2772
  ],
  [
   "15-03-2024",
   8,
   2780
  ],
  [
   "16-03-2024",
   1,
   2781
  ],
  [
   "17-03-2024",
   2,
   2783
  ],
  [
   "18-03-2024",
   2,
   2785
  ],
  [
   "19-03-2024",
   4,
   2789
  ],
  [
   "20-03-2024",
   3,
   2792
  ],
  [
   "21-03-2024",
   5,
   2797
  ],
  [
   "22-03-2024",
   1,
   2798
  ],
  [
   "23-03-2024",
   3,
   2801
  ],
  [
   "24-03-2024",
   0,
   2801
  ],
  [
   "25-03-2024",
   1,
   2802
  ],
  [
   "26-03-2024",
   5,
   2807
  ],
  [
   "27-03-2024",
   0,
   2807
  ],
  [
   "28-03-2024",
   2,
   2809
  ],
  [
   "29-03-2024",
   5,
   2814
  ],
  [
   "30-03-2024",
   4,
   2818
  ],
  [
   "31-03-2024",
   4,
   2822
  ],
  [
   "01-04-2024",
   2,
   2824
  ]
 ]
}