{
 "SigNoz/signoz": [
  [
   "21-12-2025",
   8,
   24956
  ],
  [
   "22-12-2025",
   11,
   24967
  ],
  [
   "23-12-2025",
   12,
   24979
  ],
  [
   "24-12-2025",
   6,
   24985
  ],
  [
   "25-12-2025",
   14,
   24999
  ],
  [
   "26-12-2025",
   8,
   25007
  ],
  [
   "27-12-2025",
   11,
   25018
  ],
  [
   "28-12-2025",
   9,
   25027
  ],
  [
   "29-12-2025",
   14,
   25041
  ],
  [
   "30-12-2025",
   14,
   25055
  ],
  [
   "31-12-2025",
   11,
   25066
  ],
  [
   "01-01-2026",
   10,
   25076
  ],
  [
   "02-01-2026",
   5,
   25081
  ],
  [
   "03-01-2026",
   14,
   25095
  ],
  [
   "04-01-2026",
   15,
   25110
  ],
  [
   "05-01-2026",
   14,
   25124
  ],
  [
   "06-01-2026",
   20,
   25144
  ],
  [
   "07-01-2026",
   9,
   25153
  ],
  [
   "08-01-2026",
   10,
   25163
  ],
  [
   "09-01-2026",
   10,
   25173
  ],
  [
   "10-01-2026",
   8,
   25181
  ],
  [
   "11-01-2026",
   14,
   25195
  ],
  [
   "12-01-2026",
   18,
   25213
  ],
  [
   "13-01-2026",
   19,
   25232
  ],
  [
   "14-01-2026",
   25,
   25257
  ],
  [
   "15-01-2026",
   15,
   25272
  ],
  [
   "16-01-2026",
   20,
   25292
  ],
  [
   "17-01-2026",
   13,
   25305
  ],
  [
   "18-01-2026",
   15,
   25320
  ],
  [
   "19-01-2026",
   12,
   25332
  ]
 ],
 "VictoriaMetrics/VictoriaMetrics": [
  [
   "21-12-2025",
   7,
   15720
  ],
  [
   "22-12-2025",
   15,
   15735
  ],
  [
   "23-12-2025",
   15,
   15750
  ],
  [
   "24-12-2025",
   16,
   15766
  ],
  [
   "25-12-2025",
   18,
   15784
  ],
  [
   "26-12-2025",
   10,
   15794
  ],
  [
   "27-12-2025",
   5,
   15799
  ],
  [
   "28-12-2025",
   9,
   15808
  ],
  [
   "29-12-2025",
   6,
   15814
  ],
  [
   "30-12-2025",
   5,
   15819
  ],
  [
   "31-12-2025",
   5,
   15824
  ],
  [
   "01-01-2026",
   8,
   15832
  ],
  [
   "02-01-2026",
   6,
   15838
  ],
  [
   "03-01-2026",
   4,
   15842
  ],
  [
   "04-01-2026",
   8,
   15850
  ],
  [
   "05-01-2026",
   9,
   15859
  ],
  [
   "06-01-2026",
   7,
   15866
  ],
  [
   "07-01-2026",
   17,
   15883
  ],
  [
   "08-01-2026",
   9,
   15892
  ],
  [
   "09-01-2026",
   13,
   15905
  ],
  [
   "10-01-2026",
   5,
   15910
  ],
  [
   "11-01-2026",
   9,
   15919
  ],
  [
   "12-01-2026",
   13,
   15932
  ],
  [
   "13-01-2026",
   16,
   15948
  ],
  [
   "14-01-2026",
   16,
   15964
  ],
  [
   "15-01-2026",
   43,
   16007
  ],
  [
   "16-01-2026",
   19,
   16026
  ],
  [
   "17-01-2026",
   15,
   16041
  ],
  [
   "18-01-2026",
   13,
   16054
  ],
  [
   "19-01-2026",
   16,
   16070
  ]
 ],
 "coroot/coroot": [
  [
   "21-12-2025",
   1,
   7258
  ],
  [
   "22-12-2025",
   3,
   7261
  ],
  [
   "23-12-2025",
   3,
   7264
  ],
  [
   "24-12-2025",
   1,
   7265
  ],
  [
   "25-12-2025",
   6,
   7271
  ],
  [
   "26-12-2025",
   4,
   7275
  ],
  [
   "27-12-2025",
   2,
   7277
  ],
  [
   "28-12-2025",
   1,
   7278
  ],
  [
   "29-12-2025",
   3,
   7281
  ],
  [
   "30-12-2025",
   5,
   7286
  ],
  [
   "31-12-2025",
   4,
   7290
  ],
  [
   "01-01-2026",
   0,
   7290
  ],
  [
   "02-01-2026",
   3,
   7293
  ],
  [
   "03-01-2026",
   2,
   7295
  ],
  [
   "04-01-2026",
   1,
   7296
  ],
  [
   "05-01-2026",
   0,
   7296
  ],
  [
   "06-01-2026",
   4,
   7300
  ],
  [
   "07-01-2026",
   6,
   7306
  ],
  [
   "08-01-2026",
   1,
   7307
  ],
  [
   "09-01-2026",
   4,
   7311
  ],
  [
   "10-01-2026",
   12,
   7323
  ],
  [
   "11-01-2026",
   3,
   7326
  ],
  [
   "12-01-2026",
   3,
   7329
  ],
  [
   "13-01-2026",
   4,
   7333
  ],
  [
   "14-01-2026",
   2,
   7335
  ],
  [
   "15-01-2026",
   1,
   7336
  ],
  [
   "16-01-2026",
   3,
   7339
  ],
  [
   "17-01-2026",
   0,
   7339
  ],
  [
   "18-01-2026",
   1,
   7340
  ],
  [
   "19-01-2026",
   1,
   7341
  ]
 ],
 "grafana/tempo": [
  [
   "21-12-2025",
   1,
   4933
  ],
  [
   "22-12-2025",
   5,
   4938
  ],
  [
   "23-12-2025",
   3,
   4941
  ],
  [
   "24-12-2025",
   3,
   4944
  ],
  [
   "25-12-2025",
   2,
   4946
  ],
  [
   "26-12-2025",
   1,
   4947
  ],
  [
   "27-12-2025",
   0,
   4947
  ],
  [
   "28-12-2025",
   4,
   4951
  ],
  [
   "29-12-2025",
   2,
   4953
  ],
  [
   "30-12-2025",
   1,
   4954
  ],
  [
   "31-12-2025",
   3,
   4957
  ],
  [
   "01-01-2026",
   2,
   4959
  ],
  [
   "02-01-2026",
   3,
   4962
  ],
  [
   "03-01-2026",
   1,
   4963
  ],
  [
   "04-01-2026",
   2,
   4965
  ],
  [
   "05-01-2026",
   4,
   4969
  ],
  [
   "06-01-2026",
   4,
   4973
  ],
  [
   "07-01-2026",
   4,
   4977
  ],
  [
   "08-01-2026",
   0,
   4977
  ],
  [
   "09-01-2026",
   0,
   4977
  ],
  [
   "10-01-2026",
   1,
   4978
  ],
  [
   "11-01-2026",
   4,
   4982
  ],
  [
   "12-01-2026",
   1,
   4983
  ],
  [
   "13-01-2026",
   5,
   4988
  ],
  [
   "14-01-2026",
   2,
   4990
  ],
  [
   "15-01-2026",
   3,
   4993
  ],
  [
   "16-01-2026",
   4,
   4997
  ],
  [
   "17-01-2026",
   3,
   5000
  ],
  [
   "18-01-2026",
   1,
   5001
  ],
  [
   "19-01-2026",
   1,
   5002
  ]
 ],
 "highlight/highlight": [
  [
   "21-12-2025",
   0,
   9033
  ],
  [
   "22-12-2025",
   0,
   9033
  ],
  [
   "23-12-2025",
   4,
   9037
  ],
  [
   "24-12-2025",
   3,
   9040
  ],
  [
   "25-12-2025",
   0,
   9040
  ],
  [
   "26-12-2025",
   2,
   9042
  ],
  [
   "27-12-2025",
   2,
   9044
  ],
  [
   "28-12-2025",
   1,
   9045
  ],
  [
   "29-12-2025",
   3,
   9048
  ],
  [
   "30-12-2025",
   1,
   9049
  ],
  [
   "31-12-2025",
   1,
   9050
  ],
  [
   "01-01-2026",
   3,
   9053
  ],
  [
   "02-01-2026",
   0,
   9053
  ],
  [
   "03-01-2026",
   0,
   9053
  ],
  [
   "04-01-2026",
   2,
   9055
  ],
  [
   "05-01-2026",
   1,
   9056
  ],
  [
   "06-01-2026",
   1,
   9057
  ],
  [
   "07-01-2026",
   4,
   9061
  ],
  [
   "08-01-2026",
   1,
   9062
  ],
  [
   "09-01-2026",
   3,
   9065
  ],
  [
   "10-01-2026",
   3,
   9068
  ],
  [
   "11-01-2026",
   3,
   9071
  ],
  [
   "12-01-2026",
   1,
   9072
  ],
  [
   "13-01-2026",
   3,
   9075
  ],
  [
   "14-01-2026",
   2,
   9077
  ],
  [
   "15-01-2026",
   0,
   9077
  ],
  [
   "16-01-2026",
   2,
   9079
  ],
  [
   "17-01-2026",
   1,
   9080
  ],
  [
   "18-01-2026",
   0,
   9080
  ],
  [
   "19-01-2026",
   1,
   9081
  ]
 ],
 "hyperdxio/hyperdx": [
  [
   "21-12-2025",
   0,
   9163
  ],
  [
   "22-12-2025",
   4,
   9167
  ],
  [
   "23-12-2025",
   1,
   9168
  ],
  [
   "24-12-2025",
   3,
   9171
  ],
  [
   "25-12-2025",
   4,
   9175
  ],
  [
   "26-12-2025",
   0,
   9175
  ],
  [
   "27-12-2025",
   2,
   9177
  ],
  [
   "28-12-2025",
   4,
   9181
  ],
  [
   "29-12-2025",
   2,
   9183
  ],
  [
   "30-12-2025",
   4,
   9187
  ],
  [
   "31-12-2025",
   2,
   9189
  ],
  [
   "01-01-2026",
   3,
   9192
  ],
  [
   "02-01-2026",
   2,
   9194
  ],
  [
   "03-01-2026",
   3,
   9197
  ],
  [
   "04-01-2026",
   4,
   9201
  ],
  [
   "05-01-2026",
   2,
   9203
  ],
  [
   "06-01-2026",
   5,
   9208
  ],
  [
   "07-01-2026",
   4,
   9212
  ],
  [
   "08-01-2026",
   3,
   9215
  ],
  [
   "09-01-2026",
   4,
   9219
  ],
  [
   "10-01-2026",
   5,
   9224
  ],
  [
   "11-01-2026",
   5,
   9229
  ],
  [
   "12-01-2026",
   1,
   9230
  ],
  [
   "13-01-2026",
   1,
   9231
  ],
  [
   "14-01-2026",
   4,
   9235
  ],
  [
   "15-01-2026",
   0,
   9235
  ],
  [
   "16-01-2026",
   6,
   9241
  ],
  [
   "17-01-2026",
   2,
   9243
  ],
  [
   "18-01-2026",
   3,
   9246
  ],
  [
   "19-01-2026",
   3,
   9249
  ]
 ],
 "jaegertracing/jaeger": [
  [
   "21-12-2025",
   2,
   22227
  ],
  [
   "22-12-2025",
   4,
   22231
  ],
  [
   "23-12-2025",
   7,
   22238
  ],
  [
   "24-12-2025",
   3,
   22241
  ],
  [
   "25-12-2025",
   6,
   22247
  ],
  [
   "26-12-2025",
   4,
   22251
  ],
  [
   "27-12-2025",
   3,
   22254
  ],
  [
   "28-12-2025",
   4,
   22258
  ],
  [
   "29-12-2025",
   6,
   22264
  ],
  [
   "30-12-2025",
   6,
   22270
  ],
  [
   "31-12-2025",
   5,
   22275
  ],
  [
   "01-01-2026",
   2,
   22277
  ],
  [
   "02-01-2026",
   5,
   22282
  ],
  [
   "03-01-2026",
   6,
   22288
  ],
  [
   "04-01-2026",
   6,
   22294
  ],
  [
   "05-01-2026",
   2,
   22296
  ],
  [
   "06-01-2026",
   7,
   22303
  ],
  [
   "07-01-2026",
   7,
   22310
  ],
  [
   "08-01-2026",
   4,
   22314
  ],
  [
   "09-01-2026",
   4,
   22318
  ],
  [
   "10-01-2026",
   3,
   22321
  ],
  [
   "11-01-2026",
   8,
   22329
  ],
  [
   "12-01-2026",
   3,
   22332
  ],
  [
   "13-01-2026",
   6,
   22338
  ],
  [
   "14-01-2026",
   9,
   22347
  ],
  [
   "15-01-2026",
   4,
   22351
  ],
  [
   "16-01-2026",
   1,
   22352
  ],
  [
   "17-01-2026",
   5,
   22357
  ],
  [
   "18-01-2026",
   0,
   22357
  ],
  [
   "19-01-2026",
   6,
   22363
  ]
 ],
 "keyval-dev/odigos": [
  [
   "21-12-2025",
   3,
   3595
  ],
  [
   "22-12-2025",
   1,
   3596
  ],
  [
   "23-12-2025",
   1,
   3597
  ],
  [
   "24-12-2025",
   1,
   3598
  ],
  [
   "25-12-2025",
   0,
   3598
  ],
  [
   "26-12-2025",
   0,
   3598
  ],
  [
   "27-12-2025",
   0,
   3598
  ],
  [
   "28-12-2025",
   0,
   3598
  ],
  [
   "29-12-2025",
   1,
   3599
  ],
  [
   "30-12-2025",
   0,
   3599
  ],
  [
   "31-12-2025",
   0,
   3599
  ],
  [
   "01-01-2026",
   1,
   3600
  ],
  [
   "02-01-2026",
   0,
   3600
  ],
  [
   "03-01-2026",
   0,
   3600
  ],
  [
   "04-01-2026",
   1,
   3601
  ],
  [
   "05-01-2026",
   0,
   3601
  ],
  [
   "06-01-2026",
   1,
   3602
  ],
  [
   "07-01-2026",
   1,
   3603
  ],
  [
   "08-01-2026",
   2,
   3605
  ],
  [
   "09-01-2026",
   0,
   3605
  ],
  [
   "10-01-2026",
   0,
   3605
  ],
  [
   "11-01-2026",
   0,
   3605
  ],
  [
   "12-01-2026",
   0,
   3605
  ],
  [
   "13-01-2026",
   0,
   3605
  ],
  [
   "14-01-2026",
   0,
   3605
  ],
  [
   "15-01-2026",
   1,
   3606
  ],
  [
   "16-01-2026",
   1,
   3607
  ],
  [
   "17-01-2026",
   0,
   3607
  ],
  [
   "18-01-2026",
   0,
   3607
  ],
  [
   "19-01-2026",
   1,
   3608
  ]
 ],
 "openobserve/openobserve": [
  [
   "21-12-2025",
   7,
   17525
  ],
  [
   "22-12-2025",
   9,
   17534
  ],
  [
   "23-12-2025",
   7,
   17541
  ],
  [
   "24-12-2025",
   16,
   17557
  ],
  [
   "25-12-2025",
   10,
   17567
  ],
  [
   "26-12-2025",
   12,
   17579
  ],
  [
   "27-12-2025",
   7,
   17586
  ],
  [
   "28-12-2025",
   6,
   17592
  ],
  [
   "29-12-2025",
   7,
   17599
  ],
  [
   "30-12-2025",
   3,
   17602
  ],
  [
   "31-12-2025",
   6,
   17608
  ],
  [
   "01-01-2026",
   5,
   17613
  ],
  [
   "02-01-2026",
   6,
   17619
  ],
  [
   "03-01-2026",
   1,
   17620
  ],
  [
   "04-01-2026",
   4,
   17624
  ],
  [
   "05-01-2026",
   8,
   17632
  ],
  [
   "06-01-2026",
   9,
   17641
  ],
  [
   "07-01-2026",
   7,
   17648
  ],
  [
   "08-01-2026",
   6,
   17654
  ],
  [
   "09-01-2026",
   9,
   17663
  ],
  [
   "10-01-2026",
   7,
   17670
  ],
  [
   "11-01-2026",
   6,
   17676
  ],
  [
   "12-01-2026",
   2,
   17678
  ],
  [
   "13-01-2026",
   3,
   17681
  ],
  [
   "14-01-2026",
   12,
   17693
  ],
  [
   "15-01-2026",
   11,
   17704
  ],
  [
   "16-01-2026",
   13,
   17717
  ],
  [
   "17-01-2026",
   8,
   17725
  ],
  [
   "18-01-2026",
   3,
   17728
  ],
  [
   "19-01-2026",
   5,
   17733
  ]
 ],
 "openzipkin/zipkin": [
  [
   "21-12-2025",
   1,
   17365
  ],
  [
   "22-12-2025",
   0,
   17365
  ],
  [
   "23-12-2025",
   0,
   17365
  ],
  [
   "24-12-2025",
   0,
   17365
  ],
  [
   "25-12-2025",
   0,
   17365
  ],
  [
   "26-12-2025",
   2,
   17367
  ],
  [
   "27-12-2025",
   0,
   17367
  ],
  [
   "28-12-2025",
   0,
   17367
  ],
  [
   "29-12-2025",
   0,
   17367
  ],
  [
   "30-12-2025",
   4,
   17371
  ],
  [
   "31-12-2025",
   2,
   17373
  ],
  [
   "01-01-2026",
   1,
   17374
  ],
  [
   "02-01-2026",
   1,
   17375
  ],
  [
   "03-01-2026",
   1,
   17376
  ],
  [
   "04-01-2026",
   1,
   17377
  ],
  [
   "05-01-2026",
   1,
   17378
  ],
  [
   "06-01-2026",
   4,
   17382
  ],
  [
   "07-01-2026",
   1,
   17383
  ],
  [
   "08-01-2026",
   0,
   17383
  ],
  [
   "09-01-2026",
   1,
   17384
  ],
  [
   "10-01-2026",
   2,
   17386
  ],
  [
   "11-01-2026",
   0,
   17386
  ],
  [
   "12-01-2026",
   0,
   17386
  ],
  [
   "13-01-2026",
   2,
   17388
  ],
  [
   "14-01-2026",
   3,
   17391
  ],
  [
   "15-01-2026",
   0,
   17391
  ],
  [
   "16-01-2026",
   3,
   17394
  ],
  [
   "17-01-2026",
   0,
   17394
  ],
  [
   "18-01-2026",
   0,
   17394
  ],
  [
   "19-01-2026",
   0,
   17394
  ]
 ],
 "quickwit-oss/quickwit": [
  [
   "21-12-2025",
   5,
   10645
  ],
  [
   "22-12-2025",
   6,
   10651
  ],
  [
   "23-12-2025",
   3,
   10654
  ],
  [
   "24-12-2025",
   4,
   10658
  ],
  [
   "25-12-2025",
   1,
   10659
  ],
  [
   "26-12-2025",
   0,
   10659
  ],
  [
   "27-12-2025",
   9,
   10668
  ],
  [
   "28-12-2025",
   13,
   10681
  ],
  [
   "29-12-2025",
   8,
   10689
  ],
  [
   "30-12-2025",
   0,
   10689
  ],
  [
   "31-12-2025",
   2,
   10691
  ],
  [
   "01-01-2026",
   5,
   10696
  ],
  [
   "02-01-2026",
   1,
   10697
  ],
  [
   "03-01-2026",
   8,
   10705
  ],
  [
   "04-01-2026",
   4,
   10709
  ],
  [
   "05-01-2026",
   2,
   10711
  ],
  [
   "06-01-2026",
   10,
   10721
  ],
  [
   "07-01-2026",
   13,
   10734
  ],
  [
   "08-01-2026",
   4,
   10738
  ],
  [
   "09-01-2026",
   1,
   10739
  ],
  [
   "10-01-2026",
   4,
   10743
  ],
  [
   "11-01-2026",
   9,
   10752
  ],
  [
   "12-01-2026",
   3,
   10755
  ],
  [
   "13-01-2026",
   5,
   10760
  ],
  [
   "14-01-2026",
   9,
   10769
  ],
  [
   "15-01-2026",
   1,
   10770
  ],
  [
   "16-01-2026",
   2,
   10772
  ],
  [
   "17-01-2026",
   5,
   10777
  ],
  [
   "18-01-2026",
   5,
   10782
  ],
  [
   "19-01-2026",
   3,
   10785
  ]
 ],
 "uptrace/uptrace": [
  [
   "21-12-2025",
   1,
   3998
  ],
  [
   "22-12-2025",
   2,
   4000
  ],
  [
   "23-12-2025",
   4,
   4004
  ],
  [
   "24-12-2025",
   0,
   4004
  ],
  [
   "25-12-2025",
   1,
   4005
  ],
  [
   "26-12-2025",
   0,
   4005
  ],
  [
   "27-12-2025",
   3,
   4008
  ],
  [
   "28-12-2025",
   1,
   4009
  ],
  [
   "29-12-2025",
   0,
   4009
  ],
  [
   "30-12-2025",
   0,
   4009
  ],
  [
   "31-12-2025",
   2,
   4011
  ],
  [
   "01-01-2026",
   0,
   4011
  ],
  [
   "02-01-2026",
   2,
   4013
  ],
  [
   "03-01-2026",
   0,
   4013
  ],
  [
   "04-01-2026",
   1,
   4014
  ],
  [
   "05-01-2026",
   1,
   4015
  ],
  [
   "06-01-2026",
   1,
   4016
  ],
  [
   "07-01-2026",
   2,
   4018
  ],
  [
   "08-01-2026",
   2,
   4020
  ],
  [
   "09-01-2026",
   2,
   4022
  ],
  [
   "10-01-2026",
   0,
   4022
  ],
  [
   "11-01-2026",
   1,
   4023
  ],
  [
   "12-01-2026",
   0,
   4023
  ],
  [
   "13-01-2026",
   1,
   4024
  ],
  [
   "14-01-2026",
   2,
   4026
  ],
  [
   "15-01-2026",
   3,
   4029
  ],
  [
   "16-01-2026",
   3,
   4032
  ],
  [
   "17-01-2026",
   5,
   4037
  ],
  [
   "18-01-2026",
   2,
   4039
  ],
  [
   "19-01-2026",
   2,
   4041
  ]
 ]
}